commands/__init__.py
commands/dashboard.py
commands/export.py
commands/inputs.py
commands/markdown.py
commands/presets.py
commands/scaffold.py
core/__init__.py
core/html_report.py
core/metrics_base.py
core/parser.py
core/pipeline.py
core/registry.py
core/report.py
core/utils.py
core/types/__init__.py
core/types/base.py
core/types/cli.py
core/types/config.py
dashboard/__init__.py
dashboard/server.py
metrics/__init__.py
metrics/clipscore.py
metrics/lpips.py
metrics/psnr.py
metrics/ssim.py
metrics/tlpips.py
metrics/tof.py
metrics/vbench.py
metrics/visionreward.py
metrics/vmaf.py
presets/__init__.py
presets/all.py
presets/basic.py
presets/fast.py
presets/similarity.py
presets/vbench.py
pytransform/__init__.py
surveyor2/__init__.py
surveyor2/cli.py
surveyor2/driver.py
surveyor2/assets/visionreward/questions.txt
surveyor2/assets/visionreward/weight.json
surveyor2/commands/__init__.py
surveyor2/commands/dashboard.py
surveyor2/commands/export.py
surveyor2/commands/inputs.py
surveyor2/commands/markdown.py
surveyor2/commands/presets.py
surveyor2/commands/scaffold.py
surveyor2/core/__init__.py
surveyor2/core/html_report.py
surveyor2/core/metrics_base.py
surveyor2/core/parser.py
surveyor2/core/pipeline.py
surveyor2/core/registry.py
surveyor2/core/report.py
surveyor2/core/utils.py
surveyor2/core/types/__init__.py
surveyor2/core/types/base.py
surveyor2/core/types/cli.py
surveyor2/core/types/config.py
surveyor2/dashboard/__init__.py
surveyor2/dashboard/server.py
surveyor2/metrics/__init__.py
surveyor2/metrics/clipscore.py
surveyor2/metrics/lpips.py
surveyor2/metrics/psnr.py
surveyor2/metrics/ssim.py
surveyor2/metrics/tlpips.py
surveyor2/metrics/tof.py
surveyor2/metrics/vbench.py
surveyor2/metrics/visionreward.py
surveyor2/metrics/vmaf.py
surveyor2/presets/__init__.py
surveyor2/presets/all.py
surveyor2/presets/basic.py
surveyor2/presets/fast.py
surveyor2/presets/similarity.py
surveyor2/presets/vbench.py
surveyor2-0.2.0.dist-info/licenses/LICENSE
surveyor2-0.2.0.dist-info/METADATA
surveyor2-0.2.0.dist-info/WHEEL
surveyor2-0.2.0.dist-info/entry_points.txt
surveyor2-0.2.0.dist-info/top_level.txt
surveyor2-0.2.0.dist-info/RECORD
