Metadata-Version: 2.4
Name: surveyor2
Version: 0.2.0
Summary: Video quality evaluation toolkit with comprehensive metrics
Author: Moonmath AI
License: Apache-2.0
Keywords: video,quality,evaluation,metrics,vbench,lpips,vmaf
Classifier: Development Status :: 4 - Beta
Classifier: Intended Audience :: Developers
Classifier: Intended Audience :: Science/Research
Classifier: Topic :: Scientific/Engineering :: Image Processing
Classifier: Topic :: Multimedia :: Video
Classifier: Programming Language :: Python :: 3
Classifier: Programming Language :: Python :: 3.9
Classifier: Programming Language :: Python :: 3.10
Classifier: Programming Language :: Python :: 3.11
Classifier: Programming Language :: Python :: 3.12
Classifier: License :: OSI Approved :: Apache Software License
Requires-Python: >=3.9
License-File: LICENSE
Requires-Dist: numpy<=1.26.4,>=1.23
Requires-Dist: pillow>=9
Requires-Dist: imageio[ffmpeg]>=2.35
Requires-Dist: tqdm>=4.65
Requires-Dist: pyyaml>=6.0
Requires-Dist: torch<2.6,>=2.0
Requires-Dist: torchvision>=0.15
Requires-Dist: torchaudio>=2.0
Requires-Dist: lpips>=0.1.4
Requires-Dist: open_clip_torch>=2.24.0
Requires-Dist: opencv-python>=4.8
Requires-Dist: vbench>=0.1.0
Requires-Dist: timm>=0.6.0
Requires-Dist: einops>=0.7.0
Requires-Dist: boto3
Requires-Dist: cython>=3.0
Requires-Dist: easydict
Requires-Dist: fairscale>=0.4.4
Requires-Dist: lvis
Requires-Dist: matplotlib
Requires-Dist: omegaconf
Requires-Dist: pycocoevalcap
Requires-Dist: pyiqa
Requires-Dist: scikit-image
Requires-Dist: scikit-learn
Requires-Dist: tensorboard
Provides-Extra: dev
Requires-Dist: pytest>=7; extra == "dev"
Requires-Dist: pytest-cov>=4; extra == "dev"
Requires-Dist: pyarmor; extra == "dev"
Requires-Dist: build; extra == "dev"
Requires-Dist: twine; extra == "dev"
Provides-Extra: dashboard
Requires-Dist: flask>=2.0; extra == "dashboard"
Dynamic: license-file
